Workbook

Sheet Quotation
A1: QUOTATION
A2: Company Details | E2: Quotation No. | G2: TS/2025-26/565
A3: TECH SUPPORT I & E | E3: Date: | G3: =TODAY() -> 46021
A4: J-72/73- MIDC, Bhosari, Pune
E5: Contact: | G5: 9879914828
A6: Email : techscnc@gmail.com | E6: Pan No.
E7: GST No.
A8: Customer Name | B8: Pune Instrumentation Pvt. Ltd. | E8: Email | F8: datta.survase@pipl-tech.com
A9: Address | B9: MIDC, Bhosari, Pune
A10: Name | B10: Datta Survase | E10: Mob. No. | G10: 77090 09727
A11: Sr. No. | B11: Drawing No. | C11: Part Description | D11: Processes | E11: Rate | F11: Qty/Set | G11: Cost
A12: ='Costing break up'!A2 -> 1 | B12: ='Costing break up'!B2 -> Side Plate | C12: ='Costing break up'!C2 -> 260 X 159 X 18 | D12: =IF('Costing break up'!G2>0,"CNC Waterjet Cutting, ","") -> CNC Waterjet Cutting, | E12: ='Costing break up'!M2 -> 741.97226 | F12: ='Costing break up'!N2 -> 12 | G12: ='Costing break up'!O2 -> 8903.6671
A13: ='Costing break up'!A3 -> 2 | B13: ='Costing break up'!B3 -> Bottom Support Plate | C13: ='Costing break up'!C3 -> 265 X 160 X 22 | D13: =IF('Costing break up'!G3>0,"CNC Waterjet Cutting, ","") -> CNC Waterjet Cutting, | E13: ='Costing break up'!M3 -> 1553.077 | F13: ='Costing break up'!N3 -> 6 | G13: ='Costing break up'!O3 -> 9318.462
A14: ='Costing break up'!A4 -> 3 | B14: ='Costing break up'!B4 -> Stiffner - II | C14: ='Costing break up'!C4 -> 115 X 55 X 22 | D14: =IF('Costing break up'!G4>0,"CNC Waterjet Cutting, ","") -> CNC Waterjet Cutting, | E14: ='Costing break up'!M4 -> 431.1892 | F14: ='Costing break up'!N4 -> 10 | G14: ='Costing break up'!O4 -> 4311.892
A15: ='Costing break up'!A5 -> 4 | B15: ='Costing break up'!B5 -> Stiffner | C15: ='Costing break up'!C5 -> 147 X 50 X 22 | D15: =IF('Costing break up'!G5>0,"CNC Waterjet Cutting, ","") -> CNC Waterjet Cutting, | E15: ='Costing break up'!M5 -> 504.5152 | F15: ='Costing break up'!N5 -> 2 | G15: ='Costing break up'!O5 -> 1009.0304
A16: Total in words | C16: As per actual Set Qty. | G16: =SUM(G12:G15) -> 23543.052
A17: Terms and Conditions
A18: 1) Terms of Payment: 40% against advance with material & Against delivery for labour charges
A19: 2) The above prices are exclusive of GST Tax as per HSN CODE and other duties as applicable.
A20: 3) The transport charges would be to client scope and we are not responsible for any logistics management.
A21: 4) Proper drawing has to be provided by the client and dwg / dxf format is acceptable.
A22: 5) Waterjet/Laser cutting only will be done as per customer drawings and no secondary operation will be undertaken.
A23: 6) Job Work will be done only after receiving your material, final drawings, approval of samples.
A24: 7) The damage on account of transport after the material has left our facility would be in client scope.
A25: 8) The cutting services will be provided according to the DXF/DWG files, in case of rejection against revisions- TS will not be responsible for loss of material.
A26: 9) Raw material will be supplied as FIM for Labour work
A27: 10) The above prices are valid till 7 days from date of Quotation
A28: 11) Collect scrap within 2 days after cutting process, after that we are not responsible.
A29: Accepted by: Supplier : Name & Signature | E29: For TECH SUPPORT Payal Dhanade +91 9879914828

Sheet Costing break up
A1: Sr | B1: Drawing No | C1: Part Description | D1: Thick | E1: Material MOC | F1: Perimeter ( MM) | G1: WaterJet cutting cost | H1: No of Piercing | I1: Piercing Cost | J1: Cost Per PC with RM | K1: S Total | L1: Packing & Fwd | M1: Total | N1: Qty. | O1: Grand Total | P1: Process | S1: Customer cost | T1: total | V1: Speed (mm per Min | W1: Time in Min | X1: Cost per Time
A2: 1 | B2: Side Plate | C2: 260 X 159 X 18 | D2: 18 | E2: Copper | F2: 769 | G2: =F2*0.053*D2 -> 733.626 | H2: 1 | I2: =H2*1 -> 1 | J2: =G2+I2 -> 734.626 | K2: =J2 -> 734.626 | L2: =K2*1% -> 7.34626 | M2: =K2+L2 -> 741.97226 | N2: 12 | O2: =M2*N2 -> 8903.6671 | P2: =IF('Costing break up'!G2>0,"CNC Laser Cutting, ","") -> CNC Laser Cutting, | S2: 890 | T2: =S2*N2 -> 10680 | V2: 150 | W2: =F2/V2 -> 5.1266667 | X2: =W2*60 -> 307.6
A3: 2 | B3: Bottom Support Plate | C3: 265 X 160 X 22 | D3: 22 | E3: Copper | F3: 1270 | G3: =F3*0.055*D3 -> 1536.7 | H3: 1 | I3: =H3*1 -> 1 | J3: =G3+I3 -> 1537.7 | K3: =J3 -> 1537.7 | L3: =K3*1% -> 15.377 | M3: =K3+L3 -> 1553.077 | N3: 6 | O3: =M3*N3 -> 9318.462 | P3: =IF('Costing break up'!G3>0,"CNC Laser Cutting, ","") -> CNC Laser Cutting, | R3: =IF(G2>0,"CNC Laser Cutting, ","")& IF(#REF!>0,"Powder Coating, ","")& IF(#REF!>0,"CNC Bending ","")&"with material "&'Costing break up'!E2&" " -> #REF! | S3: 0 | T3: =S3*N3 -> 0 | V3: 130 | W3: =F3/V3 -> 9.7692308 | X3: =W3*60 -> 586.15385 | AB3: Cost Effectivity
A4: 3 | B4: Stiffner - II | C4: 115 X 55 X 22 | D4: 22 | E4: Copper | F4: 352 | G4: =F4*0.055*D4 -> 425.92 | H4: 1 | I4: =H4*1 -> 1 | J4: =G4+I4 -> 426.92 | K4: =J4 -> 426.92 | L4: =K4*1% -> 4.2692 | M4: =K4+L4 -> 431.1892 | N4: 10 | O4: =M4*N4 -> 4311.892 | P4: =IF('Costing break up'!G4>0,"CNC Laser Cutting, ","") -> CNC Laser Cutting, | S4: 0 | T4: =S4*N4 -> 0 | V4: 130 | W4: =F4/V4 -> 2.7076923 | X4: =W4*60 -> 162.46154 | AB4: Speed Calculation | AI4: Rate - Waterjet cutting
A5: 4 | B5: Stiffner | C5: 147 X 50 X 22 | D5: 22 | E5: Copper | F5: 412 | G5: =F5*0.055*D5 -> 498.52 | H5: 1 | I5: =H5*1 -> 1 | J5: =G5+I5 -> 499.52 | K5: =J5 -> 499.52 | L5: =K5*1% -> 4.9952 | M5: =K5+L5 -> 504.5152 | N5: 2 | O5: =M5*N5 -> 1009.0304 | P5: =IF('Costing break up'!G5>0,"CNC Laser Cutting, ","") -> CNC Laser Cutting, | S5: 0 | T5: =S5*N5 -> 0 | V5: 130 | W5: =F5/V5 -> 3.1692308 | X5: =W5*60 -> 190.15385 | AC5: Thickness | AD5: Speed | AE5: Thickness | AF5: SPEED | AI5: Metals | AJ5: Rate | AK5: Non-Metals | AL5: Rate
A6: 5 | G6: =F6*0.055*D6 -> 0 | I6: =H6*1 -> 0 | J6: =G6+I6 -> 0 | K6: =J6 -> 0 | L6: =K6*1% -> 0 | M6: =K6+L6 -> 0 | O6: =M6*N6 -> 0 | P6: =IF('Costing break up'!G6>0,"CNC Laser Cutting, ","") | S6: 0 | T6: =S6*N6 -> 0 | AB6: 1 | AC6: 15 | AD6: 1000 | AE6: 15 | AF6: =AC6*AD6/AE6 -> 1000 | AI6: MS | AJ6: 40 + | AK6: Rubber | AL6: 20-25 +
A7: 6 | G7: =F7*0.055*D7 -> 0 | I7: =H7*1 -> 0 | J7: =G7+I7 -> 0 | K7: =J7 -> 0 | L7: =K7*1% -> 0 | M7: =K7+L7 -> 0 | O7: =M7*N7 -> 0 | P7: =IF('Costing break up'!G7>0,"CNC Laser Cutting, ","") | Q7: Hold | S7: 0 | T7: =S7*N7 -> 0 | AI7: SS | AJ7: 40 + | AK7: Glass
A8: 7 | G8: =F8*0.055*D8 -> 0 | I8: =H8*1 -> 0 | J8: =G8+I8 -> 0 | K8: =J8 -> 0 | L8: =K8*1% -> 0 | M8: =K8+L8 -> 0 | O8: =M8*N8 -> 0 | P8: =IF('Costing break up'!G8>0,"CNC Laser Cutting, ","") | S8: 0 | T8: =S8*N8 -> 0 | AB8: Affordability Calculation | AI8: Aluminium | AJ8: 20-25 + | AK8: Acrylic
A9: 8 | G9: =F9*0.055*D9 -> 0 | I9: =H9*1 -> 0 | J9: =G9+I9 -> 0 | K9: =J9 -> 0 | L9: =K9*1% -> 0 | M9: =K9+L9 -> 0 | O9: =M9*N9 -> 0 | P9: =IF('Costing break up'!G9>0,"CNC Laser Cutting, ","") | S9: 0 | T9: =S9*N9 -> 0 | AC9: Perimeter | AD9: Speed | AE9: Minutes | AF9: Hour/s | AG9: Affordability rate | AI9: Titanium | AJ9: 40 + | AK9: PU
A10: 9 | G10: =F10*0.055*D10 -> 0 | I10: =H10*1 -> 0 | J10: =G10+I10 -> 0 | K10: =J10 -> 0 | L10: =K10*1% -> 0 | M10: =K10+L10 -> 0 | O10: =M10*N10 -> 0 | P10: =IF('Costing break up'!G10>0,"CNC Laser Cutting, ","") | S10: 0 | T10: =S10*N10 -> 0 | AB10: 1 | AC10: 2829 | AD10: 1000 | AE10: =AC10/AD10 -> 2.829 | AF10: =AE10/60 -> 0.04715 | AG10: =AF10*3700 -> 174.455 | AI10: Lead | AJ10: 40 + | AK10: PP
A11: 10 | G11: =F11*0.055*D11 -> 0 | I11: =H11*1 -> 0 | J11: =G11+I11 -> 0 | K11: =J11 -> 0 | L11: =K11*1% -> 0 | M11: =K11+L11 -> 0 | O11: =M11*N11 -> 0 | P11: =IF('Costing break up'!G11>0,"CNC Laser Cutting, ","") | S11: 0 | T11: =S11*N11 -> 0 | AI11: Copper | AJ11: 40 + | AK11: Plastic
A12: 11 | G12: =F12*0.055*D12 -> 0 | I12: =H12*1 -> 0 | J12: =G12+I12 -> 0 | K12: =J12 -> 0 | L12: =K12*1% -> 0 | M12: =K12+L12 -> 0 | O12: =M12*N12 -> 0 | P12: =IF('Costing break up'!G12>0,"CNC Laser Cutting, ","") | S12: 0 | T12: =S12*N12 -> 0
A13: 12 | G13: =F13*0.055*D13 -> 0 | I13: =H13*1 -> 0 | J13: =G13+I13 -> 0 | K13: =J13 -> 0 | L13: =K13*1% -> 0 | M13: =K13+L13 -> 0 | O13: =M13*N13 -> 0 | P13: =IF('Costing break up'!G13>0,"CNC Laser Cutting, ","") | S13: 0 | T13: =S13*N13 -> 0 | AB13: Labor charge by Per meter rate
A14: 13 | G14: =F14*0.055*D14 -> 0 | I14: =H14*1 -> 0 | J14: =G14+I14 -> 0 | K14: =J14 -> 0 | L14: =K14*1% -> 0 | M14: =K14+L14 -> 0 | O14: =M14*N14 -> 0 | P14: =IF('Costing break up'!G14>0,"CNC Laser Cutting, ","") | S14: 0 | T14: =S14*N14 -> 0 | AB14: Sr. no | AC14: Perimeter | AD14: Thickness | AE14: per meter rate | AF14: total (Rate)
A15: 14 | G15: =F15*0.055*D15 -> 0 | I15: =H15*1 -> 0 | J15: =G15+I15 -> 0 | K15: =J15 -> 0 | L15: =K15*1% -> 0 | M15: =K15+L15 -> 0 | O15: =M15*N15 -> 0 | P15: =IF('Costing break up'!G15>0,"CNC Laser Cutting, ","") | S15: 0 | T15: =S15*N15 -> 0 | AB15: 1 | AC15: =AC10 -> 2829 | AD15: =AE6 -> 15 | AE15: 8 | AF15: =AC15*AD15*AE15/1000 -> 339.48
A16: 15 | G16: =F16*0.055*D16 -> 0 | I16: =H16*1 -> 0 | J16: =G16+I16 -> 0 | K16: =J16 -> 0 | L16: =K16*1% -> 0 | M16: =K16+L16 -> 0 | O16: =M16*N16 -> 0 | P16: =IF('Costing break up'!G16>0,"CNC Laser Cutting, ","") | S16: 0 | T16: =S16*N16 -> 0
A17: 16 | G17: =F17*0.055*D17 -> 0 | I17: =H17*1 -> 0 | J17: =G17+I17 -> 0 | K17: =J17 -> 0 | L17: =K17*1% -> 0 | M17: =K17+L17 -> 0 | O17: =M17*N17 -> 0 | P17: =IF('Costing break up'!G17>0,"CNC Laser Cutting, ","") | S17: 0 | T17: =S17*N17 -> 0
A18: 17 | G18: =F18*0.055*D18 -> 0 | I18: =H18*1 -> 0 | J18: =G18+I18 -> 0 | K18: =J18 -> 0 | L18: =K18*1% -> 0 | M18: =K18+L18 -> 0 | O18: =M18*N18 -> 0 | P18: =IF('Costing break up'!G18>0,"CNC Laser Cutting, ","") | S18: 0 | T18: =S18*N18 -> 0
A19: 18 | G19: =F19*0.055*D19 -> 0 | I19: =H19*1 -> 0 | J19: =G19+I19 -> 0 | K19: =J19 -> 0 | L19: =K19*1% -> 0 | M19: =K19+L19 -> 0 | O19: =M19*N19 -> 0 | P19: =IF('Costing break up'!G19>0,"CNC Laser Cutting, ","") | S19: 0 | T19: =S19*N19 -> 0
A20: 19 | G20: =F20*0.055*D20 -> 0 | I20: =H20*1 -> 0 | J20: =G20+I20 -> 0 | K20: =J20 -> 0 | L20: =K20*1% -> 0 | M20: =K20+L20 -> 0 | O20: =M20*N20 -> 0 | P20: =IF('Costing break up'!G20>0,"CNC Laser Cutting, ","") | S20: 0 | T20: =S20*N20 -> 0
A21: 20 | G21: =F21*0.055*D21 -> 0 | I21: =H21*1 -> 0 | J21: =G21+I21 -> 0 | K21: =J21 -> 0 | L21: =K21*1% -> 0 | M21: =K21+L21 -> 0 | O21: =M21*N21 -> 0 | P21: =IF('Costing break up'!G21>0,"CNC Laser Cutting, ","") | S21: 0 | T21: =S21*N21 -> 0
A22: 21 | G22: =F22*0.055*D22 -> 0 | I22: =H22*1 -> 0 | J22: =G22+I22 -> 0 | K22: =J22 -> 0 | L22: =K22*1% -> 0 | M22: =K22+L22 -> 0 | O22: =M22*N22 -> 0 | P22: =IF('Costing break up'!G22>0,"CNC Laser Cutting, ","") | S22: 0 | T22: =S22*N22 -> 0
A23: 22 | G23: =F23*0.055*D23 -> 0 | I23: =H23*1 -> 0 | J23: =G23+I23 -> 0 | K23: =J23 -> 0 | L23: =K23*1% -> 0 | M23: =K23+L23 -> 0 | O23: =M23*N23 -> 0 | P23: =IF('Costing break up'!G23>0,"CNC Laser Cutting, ","") | S23: 0 | T23: =S23*N23 -> 0
A24: 23 | G24: =F24*0.055*D24 -> 0 | I24: =H24*1 -> 0 | J24: =G24+I24 -> 0 | K24: =J24 -> 0 | L24: =K24*1% -> 0 | M24: =K24+L24 -> 0 | O24: =M24*N24 -> 0 | P24: =IF('Costing break up'!G24>0,"CNC Laser Cutting, ","") | S24: 0 | T24: =S24*N24 -> 0
A25: 24 | G25: =F25*0.055*D25 -> 0 | I25: =H25*1 -> 0 | J25: =G25+I25 -> 0 | K25: =J25 -> 0 | L25: =K25*1% -> 0 | M25: =K25+L25 -> 0 | O25: =M25*N25 -> 0 | P25: =IF('Costing break up'!G25>0,"CNC Laser Cutting, ","") | S25: 0 | T25: =S25*N25 -> 0
A26: 25 | G26: =F26*0.055*D26 -> 0 | I26: =H26*1 -> 0 | J26: =G26+I26 -> 0 | K26: =J26 -> 0 | L26: =K26*1% -> 0 | M26: =K26+L26 -> 0 | O26: =M26*N26 -> 0 | P26: =IF('Costing break up'!G26>0,"CNC Laser Cutting, ","") | S26: 0 | T26: =S26*N26 -> 0
A27: 26 | G27: =F27*0.055*D27 -> 0 | I27: =H27*1 -> 0 | J27: =G27+I27 -> 0 | K27: =J27 -> 0 | L27: =K27*1% -> 0 | M27: =K27+L27 -> 0 | O27: =M27*N27 -> 0 | P27: =IF('Costing break up'!G27>0,"CNC Laser Cutting, ","") | S27: 0 | T27: =S27*N27 -> 0
O28: =SUM(O2:O27) -> 23543.052

Sheet Standard Rate - Quotation
A1: QUOTATION
A2: Company Details | E2: Quotation No. | G2: TS/2025-26/531
A3: TECH SUPPORT I & E | E3: Date: | G3: =TODAY() -> 46021
A4: J-72/73- MIDC, Bhosari, Pune
E5: Contact: | G5: 9879914828
A6: Email : techscnc@gmail.com | E6: Pan No.
E7: GST No.
A8: Customer Name | B8: SuRe Lines | E8: Email | F8: engineering@surelines.in
A9: Address | B9: Factory address J-405 Near Quality Circle
A10: Name | B10: MADHUSUDAN KHILAR | E10: Mob. No.
A11: Sr. No. | B11: Drawing No. | C11: Part Description | D11: Processes | E11: Rate | F11: Qty/Set | G11: Cost
A12: ='Costing break up'!A2 -> 1 | B12: ='Costing break up'!B2 -> Side Plate | C12: ='Costing break up'!C2 -> 260 X 159 X 18 | D12: =IF('Costing break up'!G2>0,"CNC Waterjet Cutting, ","") -> CNC Waterjet Cutting, | E12: =G12/F12 -> 800 | F12: 1 | G12: 800
A13: ='Costing break up'!A3 -> 2 | B13: ='Costing break up'!B3 -> Bottom Support Plate | C13: ='Costing break up'!C3 -> 265 X 160 X 22 | D13: =IF('Costing break up'!G3>0,"CNC Laser Cutting, ","") -> CNC Laser Cutting, | E13: 700 | F13: ='Costing break up'!N3 -> 6 | G13: 700
A14: Total in words | C14: As per actual Set Qty. | G14: =SUM(G12:G13) -> 1500
A15: Terms and Conditions
A16: 1) Terms of Payment: 40% against advance with material & Against delivery for labour charges
A17: 2) The above prices are exclusive of GST Tax as per HSN CODE and other duties as applicable.
A18: 3) The transport charges would be to client scope and we are not responsible for any logistics management.
A19: 4) Proper drawing has to be provided by the client and dwg / dxf format is acceptable.
A20: 5) Waterjet/Laser cutting only will be done as per customer drawings and no secondary operation will be undertaken.
A21: 6) Job Work will be done only after receiving your material, final drawings, approval of samples.
A22: 7) The damage on account of transport after the material has left our facility would be in client scope.
A23: 8) The cutting services will be provided according to the DXF/DWG files, in case of rejection against revisions- TS will not be responsible for loss of material.
A24: 9) Raw material will be supplied as FIM for Labour work
A25: 10) The above prices are valid till 7 days from date of Quotation
A26: 11) Collect scrap within 2 days after cutting process, after that we are not responsible.
A27: Accepted by: Supplier : Name & Signature | E27: For TECH SUPPORT Payal Dhanade +919879914828
